alva_machinery/__init__.py
alva_machinery/branching/__init__.py
alva_machinery/branching/aWay.py
alva_machinery/distribution/__init__.py
alva_machinery/distribution/aFit.py
alva_machinery/markov/__init__.py
alva_machinery/markov/aChain.py
alva_machinery/packing/__init__.py
alva_machinery/packing/aCircle.py
alva_machinery/tool/__init__.py
alva_machinery/tool/aBox.py
alva_machinery-0.0.6.dist-info/LICENSE.txt
alva_machinery-0.0.6.dist-info/METADATA
alva_machinery-0.0.6.dist-info/WHEEL
alva_machinery-0.0.6.dist-info/top_level.txt
alva_machinery-0.0.6.dist-info/RECORD
