Metadata-Version: 2.1
Name: alva-machinery
Version: 0.0.6
Summary: Home_made machinery for image and seq analysis
Home-page: https://github.com/alvason
Author: Alvason Zhenhua Li
Author-email: alvasonli@gmail.com
License: UNKNOWN
Project-URL: Bug Tracker for RRS, https://github.com/alvason/identifying_neurite_by_RRS/issues
Project-URL: Bug Tracker for Tcell, https://github.com/alvason/visualizing_Tcell_distribution/issues
Platform: UNKNOWN
Classifier: Development Status :: 3 - Alpha
Classifier: Intended Audience :: Science/Research
Classifier: Intended Audience :: Developers
Classifier: License :: OSI Approved :: MIT License
Classifier: Programming Language :: Python :: 3
Requires-Python: >=3.6
License-File: LICENSE.txt
